pms_encoder/__init__.py
pms_encoder/_config.py
pms_encoder/common/__init__.py
pms_encoder/common/_config.py
pms_encoder/common/_encrypt.py
pms_encoder/common/_mysql_client.py
pms_encoder/common/_redis_client.py
pms_encoder/common/_s3_client.py
pms_encoder/common/data_struct.py
pms_encoder/encoder/__init__.py
pms_encoder/encoder/_image_encoder.py
pms_encoder/encoder/_video_encoder.py
pms_encoder/encoder/processor/__init__.py
pms_encoder/encoder/processor/_image_processor.py
pms_encoder/encoder/processor/_video_processor.py
pms_encoder/encoder/redis/__init__.py
pms_encoder/encoder/redis/_progress.py
pms_encoder/encoder/repository/__init__.py
pms_encoder/encoder/repository/_file_status_repo.py
pms_encoder/encoder/repository/_image_meta_repo.py
pms_encoder/encoder/repository/_video_meta_repo.py
pms_encoder/encoder/utils/__init__.py
pms_encoder/encoder/utils/_calculate_progress.py
pms_encoder/encoder/utils/_delete_file_util.py
pms_encoder/encoder/utils/_image_ffmpeg_cmd_generator.py
pms_encoder/encoder/utils/_image_queue_object_generator.py
pms_encoder/encoder/utils/_video_ffmpeg_cmd_generator.py
pms_encoder/encoder/utils/_video_queue_object_generator.py
pms_encoder/encoder/utils/_zip_util.py
pms_encoder/encoder_factory.py
pms_encoder-1.2.7.dist-info/METADATA
pms_encoder-1.2.7.dist-info/WHEEL
pms_encoder-1.2.7.dist-info/RECORD
