Metadata-Version: 2.1
Name: pms-encoder
Version: 1.2.7
Summary: 
Author: heeyong.kwon
Author-email: heeyong.kwon@4by4inc.com
Requires-Python: >=3.10,<4.0
Classifier: Programming Language :: Python :: 3
Classifier: Programming Language :: Python :: 3.10
Classifier: Programming Language :: Python :: 3.11
Classifier: Programming Language :: Python :: 3.12
Requires-Dist: boto3
Requires-Dist: ffmpeg-python
Requires-Dist: loguru
Requires-Dist: numpy
Requires-Dist: opencv-python
Requires-Dist: pms-furiosa-processor (>=1.1.0,<1.2.0)
Requires-Dist: pms-inference-engine (>=1.2.0,<1.3.0)
Requires-Dist: pms-model-manager (>=1.3.1,<2.0.0)
Requires-Dist: pms-nvidia-processor (>=1.1.0,<1.2.0)
Requires-Dist: pymysql
Requires-Dist: pytest
Requires-Dist: pytest-asyncio
Requires-Dist: python-dotenv
Requires-Dist: redis
